convert_pa-1.0.0.dist-info/METADATA
convert_pa-1.0.0.dist-info/WHEEL
convert_pa-1.0.0.dist-info/entry_points.txt
convert_pa/__init__.py
convert_pa/convert_notations.py
convert_pa/phonetic_inventory.py
convert_pa-1.0.0.dist-info/RECORD
