Metadata-Version: 2.1
Name: convert-pa
Version: 1.0.0
Summary: Package to convert between transcription standards
Author-Email: =?utf-8?q?Spr=C3=A5kbanken?= <sprakbanken@nb.no>
License: CC0
Project-URL: Repository, https://github.com/Sprakbanken/convert_nofabet.git
Project-URL: Issues, https://github.com/Sprakbanken/convert_nofabet/issues
Requires-Python: >=3.10
